{"tier": "geometry-trigonometry", "slug": "08-bezier-curves", "title": "Bézier Curves and Splines — From Polynomial Interpolation", "prerequisites": [{"tier": "calculus", "lesson_num": "09", "description": "Taylor Series (polynomials)", "slug": "09-taylor-series"}, {"tier": "discrete-mathematics", "lesson_num": "04", "description": "Combinatorics (binomial coefficients)", "slug": "04-combinatorics"}], "sections": ["Intuition", "Prerequisites", "From First Principles", "Python Verification", "Connection to CS / Games / AI", "Check Your Understanding"]}